tggl_client/__init__.py
tggl_client/client.py
tggl_client-1.2.0.dist-info/METADATA
tggl_client-1.2.0.dist-info/WHEEL
tggl_client-1.2.0.dist-info/top_level.txt
tggl_client-1.2.0.dist-info/RECORD
