Metadata-Version: 2.1
Name: tggl-client
Version: 1.2.0
Summary: Tggl python client
Keywords: Tggl,feature flag
